LICENSE.md
MANIFEST.in
README.md
setup.cfg
setup.py
drf_vue.egg-info/PKG-INFO
drf_vue.egg-info/SOURCES.txt
drf_vue.egg-info/dependency_links.txt
drf_vue.egg-info/not-zip-safe
drf_vue.egg-info/requires.txt
drf_vue.egg-info/top_level.txt
vue/__init__.py
vue/apps.py
vue/generators.py
vue/mixins.py
vue/utils.py
vue/static/bootstrap-icons.min.css
vue/static/bootstrap.min.css
vue/static/doc.css
vue/static/jquery.js
vue/static/pace.css
vue/static/highlights/zenburn.css
vue/templates/detail_template.vue
vue/templates/list_filter_template.vue
vue/templates/vue_example.html
vue/templates/vue_example.md